{
  "info": {
    "face": "VictoriaMedium-8",
    "size": 8,
    "charset": "ISO10646"
  },
  "common": {
    "lineHeight": 8,
    "base": 7
  },
  "pages": [
    {
      "id": 0,
      "file": "VictoriaMedium-8.png"
    }
  ],
  "chars": {
    "count": 93,
    "char": [
      {
        "id": 33,
        "x": 0,
        "y": 0,
        "width": 1,
        "height": 7,
        "xoffset": 3,
        "yoffset": 0,
        "xadvance": 8,
        "page": 0,
        "chnl": 0
      },
      {
        "id": 34,
        "x": 1,
        "y": 0,
        "width": 5,
        "height": 3,
        "xoffset": 1,
        "yoffset": 4,
        "xadvance": 8,
        "page": 0,
        "chnl": 0
      },
      {
        "id": 35,
        "x": 6,
        "y": 0,
        "width": 6,
        "height": 7,
        "xoffset": 1,
        "yoffset": 0,
        "xadvance": 8,
        "page": 0,
        "chnl": 0
      },
      {
        "id": 36,
        "x": 12,
        "y": 0,
        "width": 5,
        "height": 7,
        "xoffset": 1,
        "yoffset": 0,
        "xadvance": 8,
        "page": 0,
        "chnl": 0
      },
      {
        "id": 37,
        "x": 17,
        "y": 0,
        "width": 5,
        "height": 5,
        "xoffset": 1,
        "yoffset": 1,
        "xadvance": 8,
        "page": 0,
        "chnl": 0
      },
      {
        "id": 38,
        "x": 22,
        "y": 0,
        "width": 7,
        "height": 7,
        "xoffset": 0,
        "yoffset": 0,
        "xadvance": 8,
        "page": 0,
        "chnl": 0
      },
      {
        "id": 39,
        "x": 29,
        "y": 0,
        "width": 1,
        "height": 3,
        "xoffset": 3,
        "yoffset": 4,
        "xadvance": 8,
        "page": 0,
        "chnl": 0
      },
      {
        "id": 40,
        "x": 30,
        "y": 0,
        "width": 3,
        "height": 7,
        "xoffset": 2,
        "yoffset": 0,
        "xadvance": 8,
        "page": 0,
        "chnl": 0
      },
      {
        "id": 41,
        "x": 33,
        "y": 0,
        "width": 3,
        "height": 7,
        "xoffset": 2,
        "yoffset": 0,
        "xadvance": 8,
        "page": 0,
        "chnl": 0
      },
      {
        "id": 42,
        "x": 36,
        "y": 0,
        "width": 5,
        "height": 7,
        "xoffset": 1,
        "yoffset": 0,
        "xadvance": 8,
        "page": 0,
        "chnl": 0
      },
      {
        "id": 43,
        "x": 41,
        "y": 0,
        "width": 5,
        "height": 5,
        "xoffset": 1,
        "yoffset": 1,
        "xadvance": 8,
        "page": 0,
        "chnl": 0
      },
      {
        "id": 44,
        "x": 46,
        "y": 0,
        "width": 2,
        "height": 3,
        "xoffset": 2,
        "yoffset": 0,
        "xadvance": 8,
        "page": 0,
        "chnl": 0
      },
      {
        "id": 45,
        "x": 48,
        "y": 0,
        "width": 6,
        "height": 1,
        "xoffset": 1,
        "yoffset": 3,
        "xadvance": 8,
        "page": 0,
        "chnl": 0
      },
      {
        "id": 46,
        "x": 54,
        "y": 0,
        "width": 2,
        "height": 2,
        "xoffset": 3,
        "yoffset": 0,
        "xadvance": 8,
        "page": 0,
        "chnl": 0
      },
      {
        "id": 47,
        "x": 56,
        "y": 0,
        "width": 6,
        "height": 6,
        "xoffset": 1,
        "yoffset": 0,
        "xadvance": 8,
        "page": 0,
        "chnl": 0
      },
      {
        "id": 48,
        "x": 62,
        "y": 0,
        "width": 5,
        "height": 7,
        "xoffset": 1,
        "yoffset": 0,
        "xadvance": 8,
        "page": 0,
        "chnl": 0
      },
      {
        "id": 49,
        "x": 67,
        "y": 0,
        "width": 5,
        "height": 7,
        "xoffset": 1,
        "yoffset": 0,
        "xadvance": 8,
        "page": 0,
        "chnl": 0
      },
      {
        "id": 50,
        "x": 72,
        "y": 0,
        "width": 5,
        "height": 7,
        "xoffset": 1,
        "yoffset": 0,
        "xadvance": 8,
        "page": 0,
        "chnl": 0
      },
      {
        "id": 51,
        "x": 0,
        "y": 7,
        "width": 5,
        "height": 7,
        "xoffset": 1,
        "yoffset": 0,
        "xadvance": 8,
        "page": 0,
        "chnl": 0
      },
      {
        "id": 52,
        "x": 5,
        "y": 7,
        "width": 5,
        "height": 7,
        "xoffset": 1,
        "yoffset": 0,
        "xadvance": 8,
        "page": 0,
        "chnl": 0
      },
      {
        "id": 53,
        "x": 10,
        "y": 7,
        "width": 5,
        "height": 7,
        "xoffset": 1,
        "yoffset": 0,
        "xadvance": 8,
        "page": 0,
        "chnl": 0
      },
      {
        "id": 54,
        "x": 15,
        "y": 7,
        "width": 5,
        "height": 7,
        "xoffset": 1,
        "yoffset": 0,
        "xadvance": 8,
        "page": 0,
        "chnl": 0
      },
      {
        "id": 55,
        "x": 20,
        "y": 7,
        "width": 5,
        "height": 7,
        "xoffset": 1,
        "yoffset": 0,
        "xadvance": 8,
        "page": 0,
        "chnl": 0
      },
      {
        "id": 56,
        "x": 25,
        "y": 7,
        "width": 5,
        "height": 7,
        "xoffset": 1,
        "yoffset": 0,
        "xadvance": 8,
        "page": 0,
        "chnl": 0
      },
      {
        "id": 57,
        "x": 30,
        "y": 7,
        "width": 5,
        "height": 7,
        "xoffset": 1,
        "yoffset": 0,
        "xadvance": 8,
        "page": 0,
        "chnl": 0
      },
      {
        "id": 58,
        "x": 35,
        "y": 7,
        "width": 1,
        "height": 4,
        "xoffset": 3,
        "yoffset": 2,
        "xadvance": 8,
        "page": 0,
        "chnl": 0
      },
      {
        "id": 59,
        "x": 36,
        "y": 7,
        "width": 2,
        "height": 6,
        "xoffset": 2,
        "yoffset": 0,
        "xadvance": 8,
        "page": 0,
        "chnl": 0
      },
      {
        "id": 60,
        "x": 38,
        "y": 7,
        "width": 4,
        "height": 7,
        "xoffset": 2,
        "yoffset": 0,
        "xadvance": 8,
        "page": 0,
        "chnl": 0
      },
      {
        "id": 61,
        "x": 42,
        "y": 7,
        "width": 6,
        "height": 3,
        "xoffset": 1,
        "yoffset": 2,
        "xadvance": 8,
        "page": 0,
        "chnl": 0
      },
      {
        "id": 62,
        "x": 48,
        "y": 7,
        "width": 4,
        "height": 7,
        "xoffset": 2,
        "yoffset": 0,
        "xadvance": 8,
        "page": 0,
        "chnl": 0
      },
      {
        "id": 63,
        "x": 52,
        "y": 7,
        "width": 5,
        "height": 7,
        "xoffset": 1,
        "yoffset": 0,
        "xadvance": 8,
        "page": 0,
        "chnl": 0
      },
      {
        "id": 64,
        "x": 57,
        "y": 7,
        "width": 8,
        "height": 8,
        "xoffset": 0,
        "yoffset": -1,
        "xadvance": 8,
        "page": 0,
        "chnl": 0
      },
      {
        "id": 65,
        "x": 65,
        "y": 7,
        "width": 5,
        "height": 7,
        "xoffset": 1,
        "yoffset": 0,
        "xadvance": 8,
        "page": 0,
        "chnl": 0
      },
      {
        "id": 66,
        "x": 70,
        "y": 7,
        "width": 5,
        "height": 7,
        "xoffset": 1,
        "yoffset": 0,
        "xadvance": 8,
        "page": 0,
        "chnl": 0
      },
      {
        "id": 67,
        "x": 0,
        "y": 15,
        "width": 5,
        "height": 7,
        "xoffset": 1,
        "yoffset": 0,
        "xadvance": 8,
        "page": 0,
        "chnl": 0
      },
      {
        "id": 68,
        "x": 5,
        "y": 15,
        "width": 5,
        "height": 7,
        "xoffset": 1,
        "yoffset": 0,
        "xadvance": 8,
        "page": 0,
        "chnl": 0
      },
      {
        "id": 69,
        "x": 10,
        "y": 15,
        "width": 5,
        "height": 7,
        "xoffset": 1,
        "yoffset": 0,
        "xadvance": 8,
        "page": 0,
        "chnl": 0
      },
      {
        "id": 70,
        "x": 15,
        "y": 15,
        "width": 5,
        "height": 7,
        "xoffset": 1,
        "yoffset": 0,
        "xadvance": 8,
        "page": 0,
        "chnl": 0
      },
      {
        "id": 71,
        "x": 20,
        "y": 15,
        "width": 5,
        "height": 7,
        "xoffset": 1,
        "yoffset": 0,
        "xadvance": 8,
        "page": 0,
        "chnl": 0
      },
      {
        "id": 72,
        "x": 25,
        "y": 15,
        "width": 5,
        "height": 7,
        "xoffset": 1,
        "yoffset": 0,
        "xadvance": 8,
        "page": 0,
        "chnl": 0
      },
      {
        "id": 73,
        "x": 30,
        "y": 15,
        "width": 3,
        "height": 7,
        "xoffset": 2,
        "yoffset": 0,
        "xadvance": 8,
        "page": 0,
        "chnl": 0
      },
      {
        "id": 74,
        "x": 33,
        "y": 15,
        "width": 5,
        "height": 7,
        "xoffset": 1,
        "yoffset": 0,
        "xadvance": 8,
        "page": 0,
        "chnl": 0
      },
      {
        "id": 75,
        "x": 38,
        "y": 15,
        "width": 5,
        "height": 7,
        "xoffset": 1,
        "yoffset": 0,
        "xadvance": 8,
        "page": 0,
        "chnl": 0
      },
      {
        "id": 76,
        "x": 43,
        "y": 15,
        "width": 5,
        "height": 7,
        "xoffset": 1,
        "yoffset": 0,
        "xadvance": 8,
        "page": 0,
        "chnl": 0
      },
      {
        "id": 77,
        "x": 48,
        "y": 15,
        "width": 5,
        "height": 7,
        "xoffset": 1,
        "yoffset": 0,
        "xadvance": 8,
        "page": 0,
        "chnl": 0
      },
      {
        "id": 78,
        "x": 53,
        "y": 15,
        "width": 5,
        "height": 7,
        "xoffset": 1,
        "yoffset": 0,
        "xadvance": 8,
        "page": 0,
        "chnl": 0
      },
      {
        "id": 79,
        "x": 58,
        "y": 15,
        "width": 5,
        "height": 7,
        "xoffset": 1,
        "yoffset": 0,
        "xadvance": 8,
        "page": 0,
        "chnl": 0
      },
      {
        "id": 80,
        "x": 63,
        "y": 15,
        "width": 5,
        "height": 7,
        "xoffset": 1,
        "yoffset": 0,
        "xadvance": 8,
        "page": 0,
        "chnl": 0
      },
      {
        "id": 81,
        "x": 68,
        "y": 15,
        "width": 5,
        "height": 8,
        "xoffset": 1,
        "yoffset": -1,
        "xadvance": 8,
        "page": 0,
        "chnl": 0
      },
      {
        "id": 82,
        "x": 0,
        "y": 23,
        "width": 5,
        "height": 7,
        "xoffset": 1,
        "yoffset": 0,
        "xadvance": 8,
        "page": 0,
        "chnl": 0
      },
      {
        "id": 83,
        "x": 5,
        "y": 23,
        "width": 5,
        "height": 7,
        "xoffset": 1,
        "yoffset": 0,
        "xadvance": 8,
        "page": 0,
        "chnl": 0
      },
      {
        "id": 84,
        "x": 10,
        "y": 23,
        "width": 5,
        "height": 7,
        "xoffset": 1,
        "yoffset": 0,
        "xadvance": 8,
        "page": 0,
        "chnl": 0
      },
      {
        "id": 85,
        "x": 15,
        "y": 23,
        "width": 5,
        "height": 7,
        "xoffset": 1,
        "yoffset": 0,
        "xadvance": 8,
        "page": 0,
        "chnl": 0
      },
      {
        "id": 86,
        "x": 20,
        "y": 23,
        "width": 5,
        "height": 7,
        "xoffset": 1,
        "yoffset": 0,
        "xadvance": 8,
        "page": 0,
        "chnl": 0
      },
      {
        "id": 87,
        "x": 25,
        "y": 23,
        "width": 5,
        "height": 7,
        "xoffset": 1,
        "yoffset": 0,
        "xadvance": 8,
        "page": 0,
        "chnl": 0
      },
      {
        "id": 88,
        "x": 30,
        "y": 23,
        "width": 5,
        "height": 7,
        "xoffset": 1,
        "yoffset": 0,
        "xadvance": 8,
        "page": 0,
        "chnl": 0
      },
      {
        "id": 89,
        "x": 35,
        "y": 23,
        "width": 5,
        "height": 7,
        "xoffset": 1,
        "yoffset": 0,
        "xadvance": 8,
        "page": 0,
        "chnl": 0
      },
      {
        "id": 90,
        "x": 40,
        "y": 23,
        "width": 5,
        "height": 7,
        "xoffset": 1,
        "yoffset": 0,
        "xadvance": 8,
        "page": 0,
        "chnl": 0
      },
      {
        "id": 91,
        "x": 45,
        "y": 23,
        "width": 3,
        "height": 7,
        "xoffset": 2,
        "yoffset": 0,
        "xadvance": 8,
        "page": 0,
        "chnl": 0
      },
      {
        "id": 92,
        "x": 48,
        "y": 23,
        "width": 6,
        "height": 6,
        "xoffset": 1,
        "yoffset": 0,
        "xadvance": 8,
        "page": 0,
        "chnl": 0
      },
      {
        "id": 93,
        "x": 54,
        "y": 23,
        "width": 3,
        "height": 7,
        "xoffset": 3,
        "yoffset": 0,
        "xadvance": 8,
        "page": 0,
        "chnl": 0
      },
      {
        "id": 94,
        "x": 57,
        "y": 23,
        "width": 5,
        "height": 3,
        "xoffset": 2,
        "yoffset": 4,
        "xadvance": 8,
        "page": 0,
        "chnl": 0
      },
      {
        "id": 95,
        "x": 62,
        "y": 23,
        "width": 8,
        "height": 1,
        "xoffset": 0,
        "yoffset": -1,
        "xadvance": 8,
        "page": 0,
        "chnl": 0
      },
      {
        "id": 96,
        "x": 70,
        "y": 23,
        "width": 2,
        "height": 2,
        "xoffset": 3,
        "yoffset": 5,
        "xadvance": 8,
        "page": 0,
        "chnl": 0
      },
      {
        "id": 97,
        "x": 72,
        "y": 23,
        "width": 5,
        "height": 5,
        "xoffset": 1,
        "yoffset": 0,
        "xadvance": 8,
        "page": 0,
        "chnl": 0
      },
      {
        "id": 98,
        "x": 0,
        "y": 30,
        "width": 5,
        "height": 7,
        "xoffset": 1,
        "yoffset": 0,
        "xadvance": 8,
        "page": 0,
        "chnl": 0
      },
      {
        "id": 99,
        "x": 5,
        "y": 30,
        "width": 5,
        "height": 5,
        "xoffset": 1,
        "yoffset": 0,
        "xadvance": 8,
        "page": 0,
        "chnl": 0
      },
      {
        "id": 100,
        "x": 10,
        "y": 30,
        "width": 5,
        "height": 7,
        "xoffset": 1,
        "yoffset": 0,
        "xadvance": 8,
        "page": 0,
        "chnl": 0
      },
      {
        "id": 101,
        "x": 15,
        "y": 30,
        "width": 5,
        "height": 5,
        "xoffset": 1,
        "yoffset": 0,
        "xadvance": 8,
        "page": 0,
        "chnl": 0
      },
      {
        "id": 102,
        "x": 20,
        "y": 30,
        "width": 4,
        "height": 7,
        "xoffset": 2,
        "yoffset": 0,
        "xadvance": 8,
        "page": 0,
        "chnl": 0
      },
      {
        "id": 103,
        "x": 24,
        "y": 30,
        "width": 5,
        "height": 6,
        "xoffset": 1,
        "yoffset": -1,
        "xadvance": 8,
        "page": 0,
        "chnl": 0
      },
      {
        "id": 104,
        "x": 29,
        "y": 30,
        "width": 5,
        "height": 7,
        "xoffset": 1,
        "yoffset": 0,
        "xadvance": 8,
        "page": 0,
        "chnl": 0
      },
      {
        "id": 105,
        "x": 34,
        "y": 30,
        "width": 3,
        "height": 7,
        "xoffset": 2,
        "yoffset": 0,
        "xadvance": 8,
        "page": 0,
        "chnl": 0
      },
      {
        "id": 106,
        "x": 37,
        "y": 30,
        "width": 5,
        "height": 8,
        "xoffset": 1,
        "yoffset": -1,
        "xadvance": 8,
        "page": 0,
        "chnl": 0
      },
      {
        "id": 107,
        "x": 42,
        "y": 30,
        "width": 5,
        "height": 7,
        "xoffset": 1,
        "yoffset": 0,
        "xadvance": 8,
        "page": 0,
        "chnl": 0
      },
      {
        "id": 108,
        "x": 47,
        "y": 30,
        "width": 3,
        "height": 7,
        "xoffset": 2,
        "yoffset": 0,
        "xadvance": 8,
        "page": 0,
        "chnl": 0
      },
      {
        "id": 109,
        "x": 50,
        "y": 30,
        "width": 5,
        "height": 5,
        "xoffset": 1,
        "yoffset": 0,
        "xadvance": 8,
        "page": 0,
        "chnl": 0
      },
      {
        "id": 110,
        "x": 55,
        "y": 30,
        "width": 5,
        "height": 5,
        "xoffset": 1,
        "yoffset": 0,
        "xadvance": 8,
        "page": 0,
        "chnl": 0
      },
      {
        "id": 111,
        "x": 60,
        "y": 30,
        "width": 5,
        "height": 5,
        "xoffset": 1,
        "yoffset": 0,
        "xadvance": 8,
        "page": 0,
        "chnl": 0
      },
      {
        "id": 112,
        "x": 65,
        "y": 30,
        "width": 5,
        "height": 6,
        "xoffset": 1,
        "yoffset": -1,
        "xadvance": 8,
        "page": 0,
        "chnl": 0
      },
      {
        "id": 113,
        "x": 70,
        "y": 30,
        "width": 5,
        "height": 6,
        "xoffset": 1,
        "yoffset": -1,
        "xadvance": 8,
        "page": 0,
        "chnl": 0
      },
      {
        "id": 114,
        "x": 0,
        "y": 38,
        "width": 5,
        "height": 5,
        "xoffset": 1,
        "yoffset": 0,
        "xadvance": 8,
        "page": 0,
        "chnl": 0
      },
      {
        "id": 115,
        "x": 5,
        "y": 38,
        "width": 5,
        "height": 5,
        "xoffset": 1,
        "yoffset": 0,
        "xadvance": 8,
        "page": 0,
        "chnl": 0
      },
      {
        "id": 116,
        "x": 10,
        "y": 38,
        "width": 3,
        "height": 7,
        "xoffset": 2,
        "yoffset": 0,
        "xadvance": 8,
        "page": 0,
        "chnl": 0
      },
      {
        "id": 117,
        "x": 13,
        "y": 38,
        "width": 5,
        "height": 5,
        "xoffset": 1,
        "yoffset": 0,
        "xadvance": 8,
        "page": 0,
        "chnl": 0
      },
      {
        "id": 118,
        "x": 18,
        "y": 38,
        "width": 5,
        "height": 5,
        "xoffset": 1,
        "yoffset": 0,
        "xadvance": 8,
        "page": 0,
        "chnl": 0
      },
      {
        "id": 119,
        "x": 23,
        "y": 38,
        "width": 5,
        "height": 5,
        "xoffset": 1,
        "yoffset": 0,
        "xadvance": 8,
        "page": 0,
        "chnl": 0
      },
      {
        "id": 120,
        "x": 28,
        "y": 38,
        "width": 5,
        "height": 5,
        "xoffset": 1,
        "yoffset": 0,
        "xadvance": 8,
        "page": 0,
        "chnl": 0
      },
      {
        "id": 121,
        "x": 33,
        "y": 38,
        "width": 5,
        "height": 6,
        "xoffset": 1,
        "yoffset": -1,
        "xadvance": 8,
        "page": 0,
        "chnl": 0
      },
      {
        "id": 122,
        "x": 38,
        "y": 38,
        "width": 5,
        "height": 5,
        "xoffset": 1,
        "yoffset": 0,
        "xadvance": 8,
        "page": 0,
        "chnl": 0
      },
      {
        "id": 123,
        "x": 43,
        "y": 38,
        "width": 3,
        "height": 7,
        "xoffset": 2,
        "yoffset": 0,
        "xadvance": 8,
        "page": 0,
        "chnl": 0
      },
      {
        "id": 124,
        "x": 46,
        "y": 38,
        "width": 1,
        "height": 8,
        "xoffset": 3,
        "yoffset": -1,
        "xadvance": 8,
        "page": 0,
        "chnl": 0
      },
      {
        "id": 125,
        "x": 47,
        "y": 38,
        "width": 3,
        "height": 7,
        "xoffset": 2,
        "yoffset": 0,
        "xadvance": 8,
        "page": 0,
        "chnl": 0
      }
    ]
  }
}